README
setup.py
minlp/__init__.py
minlp/infile_one.py
minlp.egg-info/PKG-INFO
minlp.egg-info/SOURCES.txt
minlp.egg-info/dependency_links.txt
minlp.egg-info/entry_points.txt
minlp.egg-info/top_level.txt
minlp/inside_one/__init__.py
minlp/inside_one/infile_two.py