Metadata-Version: 1.1
Name: minlp
Version: 6.2
Summary: just test for now.
Home-page: http://minteacher.com
Author: SUNG MIN YANG
Author-email: sungmin.nlp@gmail.com
License: GNU
Keywords: tutorial
Platform: UNKNOWN
Classifier: License :: OSI Approved :: BSD License
